buildlackey/Commands.py
buildlackey/Environment.py
buildlackey/PythonWarnings.py
buildlackey/__init__.py
buildlackey/_version.py
buildlackey/commands/Cleanup.py
buildlackey/commands/Package.py
buildlackey/commands/ProductionPush.py
buildlackey/commands/RunMypy.py
buildlackey/commands/UnitTestVerbosity.py
buildlackey/commands/UnitTests.py
buildlackey/commands/__init__.py
buildlackey/exceptions/ProjectNotSetException.py
buildlackey/exceptions/ProjectsBaseNotSetException.py
buildlackey/exceptions/__init__.py
buildlackey/resources/__init__.py
buildlackey/resources/loggingConfiguration.json
buildlackey-2.0.0.dist-info/licenses/LICENSE
buildlackey-2.0.0.dist-info/METADATA
buildlackey-2.0.0.dist-info/WHEEL
buildlackey-2.0.0.dist-info/entry_points.txt
buildlackey-2.0.0.dist-info/top_level.txt
buildlackey-2.0.0.dist-info/RECORD
