Metadata-Version: 2.4
Name: buildlackey
Version: 2.0.0
Summary: Project Maintenance Scripts
Author-email: "Humberto A. Sanchez II" <Humbert.A.Sanchez.II@gmail.com>
Maintainer-email: "Humberto A. Sanchez II" <Humbert.A.Sanchez.II@gmail.com>
License-Expression: AGPL-1.0-or-later
Project-URL: Repository, https://github.com/hasii2011/buildlackey
Keywords: developer,python
License-File: LICENSE
Requires-Dist: click>=8.2.1
Requires-Dist: html-testRunner>=1.2.1
Provides-Extra: test
Requires-Dist: html-testRunner~=1.2.1; extra == "test"
Requires-Dist: mypy==1.17.1; extra == "test"
Requires-Dist: codeallybasic==1.12.0; extra == "test"
Provides-Extra: deploy
Requires-Dist: wheel==0.45.1; extra == "deploy"
Requires-Dist: setuptools==80.9.0; extra == "deploy"
Requires-Dist: twine==6.1.0; extra == "deploy"
Requires-Dist: build==1.3.0; extra == "deploy"
Dynamic: license-file
